flake8_simple_string_first_arg.py
flake8_simple_string_first_arg-0.2.0.dist-info/LICENSE
flake8_simple_string_first_arg-0.2.0.dist-info/WHEEL
flake8_simple_string_first_arg-0.2.0.dist-info/entry_points.txt
flake8_simple_string_first_arg-0.2.0.dist-info/METADATA
flake8_simple_string_first_arg-0.2.0.dist-info/RECORD
