Metadata-Version: 2.1
Name: flake8-simple-string-first-arg
Version: 0.2.0
Summary: This Flake8 plugin for checking that first param of callable is simple string.
License: MIT
Keywords: flake8-simple-string-first-arg,flake8,plugin,simple string,first arg,simple first arg
Author: Kozyar Valeriy
Author-email: monqpepers@gmail.com
Requires-Python: >=3.9,<4.0
Classifier: Framework :: Flake8
Classifier: License :: OSI Approved :: MIT License
Classifier: Programming Language :: Python
Classifier: Programming Language :: Python :: 3
Classifier: Programming Language :: Python :: 3.9
Classifier: Programming Language :: Python :: 3.10
Classifier: Programming Language :: Python :: 3.11
Classifier: Programming Language :: Python :: 3
Classifier: Programming Language :: Python :: 3.10
Classifier: Programming Language :: Python :: 3.11
Classifier: Programming Language :: Python :: 3.9
Classifier: Topic :: Software Development :: Libraries :: Python Modules
Classifier: Topic :: Software Development :: Quality Assurance
Requires-Dist: flake8
